achakra/__init__.py
achakra/achakra.py
achakra-1.0.0.dist-info/LICENSE
achakra-1.0.0.dist-info/METADATA
achakra-1.0.0.dist-info/WHEEL
achakra-1.0.0.dist-info/top_level.txt
achakra-1.0.0.dist-info/RECORD
