Metadata-Version: 2.1
Name: achakra
Version: 1.0.0
Summary: A useful module
Home-page: UNKNOWN
Author: Aneesh Chakravarthula
Author-email: srianeesh328@gmail.com
License: UNKNOWN
Platform: UNKNOWN
License-File: LICENSE
Requires-Dist: wheel
Requires-Dist: bar
